coingate/__init__.py
coingate/client.py
coingate/constants.py
coingate/exceptions.py
coingate-0.0.5.dist-info/DESCRIPTION.rst
coingate-0.0.5.dist-info/METADATA
coingate-0.0.5.dist-info/RECORD
coingate-0.0.5.dist-info/WHEEL
coingate-0.0.5.dist-info/metadata.json
coingate-0.0.5.dist-info/top_level.txt
