Metadata-Version: 2.0
Name: coingate
Version: 0.0.5
Summary: Basic CoinGate API client
Home-page: https://github.com/iodbh/coingate-python
Author: iodbh
Author-email: iodbh@iodbh.net
License: MIT
Keywords: coingate payment
Platform: UNKNOWN
Classifier: Development Status :: 3 - Alpha
Classifier: Intended Audience :: Developers
Classifier: Topic :: Software Development :: Libraries
Classifier: License :: OSI Approved :: MIT License
Classifier: Programming Language :: Python :: 2
Classifier: Programming Language :: Python :: 3
Requires-Dist: requests
Requires-Dist: arrow
Provides-Extra: dev
Requires-Dist: pypandoc; extra == 'dev'
